musictree/__init__.py
musictree/accidental.py
musictree/beat.py
musictree/chord.py
musictree/clef.py
musictree/core.py
musictree/dynamics.py
musictree/exceptions.py
musictree/finalupdate_mixin.py
musictree/key.py
musictree/layout.py
musictree/measure.py
musictree/midi.py
musictree/note.py
musictree/part.py
musictree/quarterduration.py
musictree/score.py
musictree/staff.py
musictree/time.py
musictree/util.py
musictree/voice.py
musictree/xmlwrapper.py
musictree/MyTestSuite/__init__.py
musictree/MyTestSuite/test_1a_1_helloworld.py
musictree/MyTestSuite/test_1a_2_long_helloworld.py
musictree/MyTestSuite/test_1a_3_fractional_helloworld.py
musictree/MyTestSuite/test_1a_4_quarter_multiplications.py
musictree/MyTestSuite/test_1b_chromatic_up_1.py
musictree/MyTestSuite/test_1b_chromatic_up_2.py
musictree/MyTestSuite/test_2a_tuplets_1.py
musictree/MyTestSuite/test_2b_beams_1.py
musictree/MyTestSuite/test_3a_complex_accidentals.py
musictree/MyTestSuite/test_4a_lyrics.py
musictree/MyTestSuite/test_5a_voices.py
musictree/MyTestSuite/test_5b_staves_and_clefs.py
musictree/MyTestSuite/test_6a_1_add_x.py
musictree/MyTestSuite/test_7a_quantization.py
musictree/MyTestSuite/test_8a_chords.py
musictree/UnofficialTestSuite/__init__.py
musictree/UnofficialTestSuite/test_1_pitch_pitch.py
musictree/profiler/__init__.py
musictree/profiler/profile_quantization.py
musictree/profiler/profile_tuplets.py
musictree/profiler/time_helloworld.py
musictree/profiler/time_xml_left_margin.py
musictree/profiler/time_xml_score.py
musictree/tests/__init__.py
musictree/tests/test_accidental.py
musictree/tests/test_beat.py
musictree/tests/test_chord.py
musictree/tests/test_clef.py
musictree/tests/test_doctest.py
musictree/tests/test_dynamics.py
musictree/tests/test_final_updates.py
musictree/tests/test_get_chords.py
musictree/tests/test_gets.py
musictree/tests/test_key.py
musictree/tests/test_layout.py
musictree/tests/test_measure.py
musictree/tests/test_midi.py
musictree/tests/test_music_tree.py
musicscore2-1.3.3.dist-info/LICENSE
musicscore2-1.3.3.dist-info/METADATA
musicscore2-1.3.3.dist-info/WHEEL
musicscore2-1.3.3.dist-info/top_level.txt
musicscore2-1.3.3.dist-info/RECORD
