Metadata-Version: 2.1
Name: musicscore2
Version: 1.3.3
Summary: Generating musicxml files.
Home-page: https://github.com/alexgorji/musicscore2.git
Author: Alex Gorji
Author-email: aligorji@hotmail.com
Classifier: Programming Language :: Python :: 3
Classifier: Operating System :: OS Independent
License-File: LICENSE
Requires-Dist: musicxml
Requires-Dist: quicktions
